[{"Area_territoriale": "NORD-OVEST", "Regione": "LOMBARDIA", "Prov": "MI", "Comune_ISTAT": 3015146, "Comune_cat": "C1AA", "Sez": " ", "Comune_amm": "F205", "Comune_descrizione": "MILANO", "Fascia": "B", "Zona_Descr": "CENTRO STORICO -DUOMO, SANBABILA, MONTENAPOLEONE, MISSORI, CAIROLI", "Zona": "B12", "LinkZona": "MI00003228", "Cod_tip_prev": 20, "Descr_tip_prev": "Abitazioni civili", "Stato_prev": "N", "Microzona": 2}, {"Area_territoriale": "NORD-OVEST", "Regione": "LOMBARDIA", "Prov": "MI", "Comune_ISTAT": 3015146, "Comune_cat": "C1AA", "Sez": " ", "Comune_amm": "F205", "Comune_descrizione": "MILANO", "Fascia": "B", "Zona_Descr": "CENTRO STORICO -UNIVERSITA STATALE, SAN LORENZO", "Zona": "B13", "LinkZona": "MI00003232", "Cod_tip_prev": 20, "Descr_tip_prev": "Abitazioni civili", "Stato_prev": "N", "Microzona": 3}, {"Area_territoriale": "NORD-OVEST", "Regione": "LOMBARDIA", "Prov": "MI", "Comune_ISTAT": 3015146, "Comune_cat": "C1AA", "Sez": " ", "Comune_amm": "F205", "Comune_descrizione": "MILANO", "Fascia": "B", "Zona_Descr": "CENTRO STORICO - BRERA", "Zona": "B15", "LinkZona": "MI00003544", "Cod_tip_prev": 20, "Descr_tip_prev": "Abitazioni civili", "Stato_prev": "O", "Microzona": 0}, {"Area_territoriale": "NORD-OVEST", "Regione": "LOMBARDIA", "Prov": "MI", "Comune_ISTAT": 3015146, "Comune_cat": "C1AA", "Sez": " ", "Comune_amm": "F205", "Comune_descrizione": "MILANO", "Fascia": "B", "Zona_Descr": "CENTRO STORICO -SANT`AMBROGIO, CADORNA, VIA DANTE", "Zona": "B16", "LinkZona": "MI00003545", "Cod_tip_prev": 20, "Descr_tip_prev": "Abitazioni civili", "Stato_prev": "O", "Microzona": 0}, {"Area_territoriale": "NORD-OVEST", "Regione": "LOMBARDIA", "Prov": "MI", "Comune_ISTAT": 3015146, "Comune_cat": "C1AA", "Sez": " ", "Comune_amm": "F205", "Comune_descrizione": "MILANO", "Fascia": "B", "Zona_Descr": "PARCO SEMPIONE, ARCO DELLA PACE, CORSO MAGENTA", "Zona": "B17", "LinkZona": "MI00004767", "Cod_tip_prev": 20, "Descr_tip_prev": "Abitazioni civili", "Stato_prev": "N", "Microzona": 0}, {"Area_territoriale": "NORD-OVEST", "Regione": "LOMBARDIA", "Prov": "MI", "Comune_ISTAT": 3015146, "Comune_cat": "C1AA", "Sez": " ", "Comune_amm": "F205", "Comune_descrizione": "MILANO", "Fascia": "B", "Zona_Descr": "TURATI, MOSCOVA, CORSO VENEZIA", "Zona": "B18", "LinkZona": "MI00004768", "Cod_tip_prev": 20, "Descr_tip_prev": "Abitazioni civili", "Stato_prev": "N", "Microzona": 0}, {"Area_territoriale": "NORD-OVEST", "Regione": "LOMBARDIA", "Prov": "MI", "Comune_ISTAT": 3015146, "Comune_cat": "C1AA", "Sez": " ", "Comune_amm": "F205", "Comune_descrizione": "MILANO", "Fascia": "B", "Zona_Descr": "VENEZIA, PORTA VITTORIA, PORTA ROMANA", "Zona": "B19", "LinkZona": "MI00004769", "Cod_tip_prev": 20, "Descr_tip_prev": "Abitazioni civili", "Stato_prev": "N", "Microzona": 0}, {"Area_territoriale": "NORD-OVEST", "Regione": "LOMBARDIA", "Prov": "MI", "Comune_ISTAT": 3015146, "Comune_cat": "C1AA", "Sez": " ", "Comune_amm": "F205", "Comune_descrizione": "MILANO", "Fascia": "B", "Zona_Descr": "PORTA VIGENTINA, PORTA ROMANA", "Zona": "B20", "LinkZona": "MI00004770", "Cod_tip_prev": 20, "Descr_tip_prev": "Abitazioni civili", "Stato_prev": "N", "Microzona": 0}, {"Area_territoriale": "NORD-OVEST", "Regione": "LOMBARDIA", "Prov": "MI", "Comune_ISTAT": 3015146, "Comune_cat": "C1AA", "Sez": " ", "Comune_amm": "F205", "Comune_descrizione": "MILANO", "Fascia": "B", "Zona_Descr": "PORTA TICINESE, PORTA GENOVA, VIA SAN VITTORE", "Zona": "B21", "LinkZona": "MI00004771", "Cod_tip_prev": 20, "Descr_tip_prev": "Abitazioni civili", "Stato_prev": "N", "Microzona": 0}, {"Area_territoriale": "NORD-OVEST", "Regione": "LOMBARDIA", "Prov": "MI", "Comune_ISTAT": 3015146, "Comune_cat": "C1AA", "Sez": " ", "Comune_amm": "F205", "Comune_descrizione": "MILANO", "Fascia": "C", "Zona_Descr": "PISANI, BUENOS AIRES, REGINA GIOVANNA", "Zona": "C12", "LinkZona": "MI00000307", "Cod_tip_prev": 20, "Descr_tip_prev": "Abitazioni civili", "Stato_prev": "N", "Microzona": 22}, {"Area_territoriale": "NORD-OVEST", "Regione": "LOMBARDIA", "Prov": "MI", "Comune_ISTAT": 3015146, "Comune_cat": "C1AA", "Sez": " ", "Comune_amm": "F205", "Comune_descrizione": "MILANO", "Fascia": "C", "Zona_Descr": "CITY LIFE", "Zona": "C13", "LinkZona": "MI00003667", "Cod_tip_prev": 20, "Descr_tip_prev": "Abitazioni civili", "Stato_prev": "O", "Microzona": 0}, {"Area_territoriale": "NORD-OVEST", "Regione": "LOMBARDIA", "Prov": "MI", "Comune_ISTAT": 3015146, "Comune_cat": "C1AA", "Sez": " ", "Comune_amm": "F205", "Comune_descrizione": "MILANO", "Fascia": "C", "Zona_Descr": "PORTA NUOVA", "Zona": "C14", "LinkZona": "MI00003668", "Cod_tip_prev": 20, "Descr_tip_prev": "Abitazioni civili", "Stato_prev": "O", "Microzona": 0}, {"Area_territoriale": "NORD-OVEST", "Regione": "LOMBARDIA", "Prov": "MI", "Comune_ISTAT": 3015146, "Comune_cat": "C1AA", "Sez": " ", "Comune_amm": "F205", "Comune_descrizione": "MILANO", "Fascia": "C", "Zona_Descr": "STAZIONE CENTRALE VIALE STELVIO", "Zona": "C15", "LinkZona": "MI00003669", "Cod_tip_prev": 20, "Descr_tip_prev": "Abitazioni civili", "Stato_prev": "N", "Microzona": 0}, {"Area_territoriale": "NORD-OVEST", "Regione": "LOMBARDIA", "Prov": "MI", "Comune_ISTAT": 3015146, "Comune_cat": "C1AA", "Sez": " ", "Comune_amm": "F205", "Comune_descrizione": "MILANO", "Fascia": "C", "Zona_Descr": "CENISIO, FARINI, SARPI", "Zona": "C16", "LinkZona": "MI00004772", "Cod_tip_prev": 20, "Descr_tip_prev": "Abitazioni civili", "Stato_prev": "N", "Microzona": 0}, {"Area_territoriale": "NORD-OVEST", "Regione": "LOMBARDIA", "Prov": "MI", "Comune_ISTAT": 3015146, "Comune_cat": "C1AA", "Sez": " ", "Comune_amm": "F205", "Comune_descrizione": "MILANO", "Fascia": "C", "Zona_Descr": "SEMPIONE, PAGANO, WASHINGTON", "Zona": "C17", "LinkZona": "MI00004773", "Cod_tip_prev": 20, "Descr_tip_prev": "Abitazioni civili", "Stato_prev": "N", "Microzona": 0}, {"Area_territoriale": "NORD-OVEST", "Regione": "LOMBARDIA", "Prov": "MI", "Comune_ISTAT": 3015146, "Comune_cat": "C1AA", "Sez": " ", "Comune_amm": "F205", "Comune_descrizione": "MILANO", "Fascia": "C", "Zona_Descr": "SOLARI, P.TA GENOVA, ASCANIO SFORZA", "Zona": "C18", "LinkZona": "MI00004774", "Cod_tip_prev": 20, "Descr_tip_prev": "Abitazioni civili", "Stato_prev": "N", "Microzona": 0}, {"Area_territoriale": "NORD-OVEST", "Regione": "LOMBARDIA", "Prov": "MI", "Comune_ISTAT": 3015146, "Comune_cat": "C1AA", "Sez": " ", "Comune_amm": "F205", "Comune_descrizione": "MILANO", "Fascia": "C", "Zona_Descr": "TABACCHI, SARFATTI, CREMA", "Zona": "C19", "LinkZona": "MI00004775", "Cod_tip_prev": 20, "Descr_tip_prev": "Abitazioni civili", "Stato_prev": "N", "Microzona": 0}, {"Area_territoriale": "NORD-OVEST", "Regione": "LOMBARDIA", "Prov": "MI", "Comune_ISTAT": 3015146, "Comune_cat": "C1AA", "Sez": " ", "Comune_amm": "F205", "Comune_descrizione": "MILANO", "Fascia": "C", "Zona_Descr": "LIBIA, ,XXII MARZO, INDIPENDENZA", "Zona": "C20", "LinkZona": "MI00004776", "Cod_tip_prev": 20, "Descr_tip_prev": "Abitazioni civili", "Stato_prev": "N", "Microzona": 0}, {"Area_territoriale": "NORD-OVEST", "Regione": "LOMBARDIA", "Prov": "MI", "Comune_ISTAT": 3015146, "Comune_cat": "C1AA", "Sez": " ", "Comune_amm": "F205", "Comune_descrizione": "MILANO", "Fascia": "D", "Zona_Descr": "PARCO LAMBRO, FELTRE, UDINE", "Zona": "D10", "LinkZona": "MI00000317", "Cod_tip_prev": 20, "Descr_tip_prev": "Abitazioni civili", "Stato_prev": "N", "Microzona": 32}, {"Area_territoriale": "NORD-OVEST", "Regione": "LOMBARDIA", "Prov": "MI", "Comune_ISTAT": 3015146, "Comune_cat": "C1AA", "Sez": " ", "Comune_amm": "F205", "Comune_descrizione": "MILANO", "Fascia": "D", "Zona_Descr": "PIOLA, ARGONNE, CORSICA", "Zona": "D12", "LinkZona": "MI00000319", "Cod_tip_prev": 20, "Descr_tip_prev": "Abitazioni civili", "Stato_prev": "N", "Microzona": 34}, {"Area_territoriale": "NORD-OVEST", "Regione": "LOMBARDIA", "Prov": "MI", "Comune_ISTAT": 3015146, "Comune_cat": "C1AA", "Sez": " ", "Comune_amm": "F205", "Comune_descrizione": "MILANO", "Fascia": "D", "Zona_Descr": "LAMBRATE, RUBATTINO, ROMBON", "Zona": "D13", "LinkZona": "MI00000320", "Cod_tip_prev": 20, "Descr_tip_prev": "Abitazioni civili", "Stato_prev": "N", "Microzona": 35}, {"Area_territoriale": "NORD-OVEST", "Regione": "LOMBARDIA", "Prov": "MI", "Comune_ISTAT": 3015146, "Comune_cat": "C1AA", "Sez": " ", "Comune_amm": "F205", "Comune_descrizione": "MILANO", "Fascia": "D", "Zona_Descr": "TITO LIVIO, TERTULLIANO, LONGANESI, ORTOMERCATO", "Zona": "D16", "LinkZona": "MI00000323", "Cod_tip_prev": 20, "Descr_tip_prev": "Abitazioni civili", "Stato_prev": "N", "Microzona": 0}, {"Area_territoriale": "NORD-OVEST", "Regione": "LOMBARDIA", "Prov": "MI", "Comune_ISTAT": 3015146, "Comune_cat": "C1AA", "Sez": " ", "Comune_amm": "F205", "Comune_descrizione": "MILANO", "Fascia": "D", "Zona_Descr": "MAROCCHETTI, VIGENTINO, CHIESA ROSSA", "Zona": "D18", "LinkZona": "MI00000325", "Cod_tip_prev": 20, "Descr_tip_prev": "Abitazioni civili", "Stato_prev": "N", "Microzona": 40}, {"Area_territoriale": "NORD-OVEST", "Regione": "LOMBARDIA", "Prov": "MI", "Comune_ISTAT": 3015146, "Comune_cat": "C1AA", "Sez": " ", "Comune_amm": "F205", "Comune_descrizione": "MILANO", "Fascia": "D", "Zona_Descr": "ORTLES, SPADOLINI, BAZZI", "Zona": "D20", "LinkZona": "MI00000327", "Cod_tip_prev": 20, "Descr_tip_prev": "Abitazioni civili", "Stato_prev": "N", "Microzona": 42}, {"Area_territoriale": "NORD-OVEST", "Regione": "LOMBARDIA", "Prov": "MI", "Comune_ISTAT": 3015146, "Comune_cat": "C1AA", "Sez": " ", "Comune_amm": "F205", "Comune_descrizione": "MILANO", "Fascia": "D", "Zona_Descr": "BARONA, FAMAGOSTA, FAENZA", "Zona": "D21", "LinkZona": "MI00000328", "Cod_tip_prev": 20, "Descr_tip_prev": "Abitazioni civili", "Stato_prev": "N", "Microzona": 43}, {"Area_territoriale": "NORD-OVEST", "Regione": "LOMBARDIA", "Prov": "MI", "Comune_ISTAT": 3015146, "Comune_cat": "C1AA", "Sez": " ", "Comune_amm": "F205", "Comune_descrizione": "MILANO", "Fascia": "D", "Zona_Descr": "SEGESTA, ARETUSA, VESPRI SICILIANI", "Zona": "D24", "LinkZona": "MI00000331", "Cod_tip_prev": 20, "Descr_tip_prev": "Abitazioni civili", "Stato_prev": "N", "Microzona": 46}, {"Area_territoriale": "NORD-OVEST", "Regione": "LOMBARDIA", "Prov": "MI", "Comune_ISTAT": 3015146, "Comune_cat": "C1AA", "Sez": " ", "Comune_amm": "F205", "Comune_descrizione": "MILANO", "Fascia": "D", "Zona_Descr": "LORENTEGGIO, INGANNI, BISCEGLIE, SAN CARLO B.", "Zona": "D25", "LinkZona": "MI00000332", "Cod_tip_prev": 20, "Descr_tip_prev": "Abitazioni civili", "Stato_prev": "N", "Microzona": 47}, {"Area_territoriale": "NORD-OVEST", "Regione": "LOMBARDIA", "Prov": "MI", "Comune_ISTAT": 3015146, "Comune_cat": "C1AA", "Sez": " ", "Comune_amm": "F205", "Comune_descrizione": "MILANO", "Fascia": "D", "Zona_Descr": "IPPODROMO, CAPRILLI, MONTE STELLA", "Zona": "D28", "LinkZona": "MI00000335", "Cod_tip_prev": 20, "Descr_tip_prev": "Abitazioni civili", "Stato_prev": "N", "Microzona": 50}, {"Area_territoriale": "NORD-OVEST", "Regione": "LOMBARDIA", "Prov": "MI", "Comune_ISTAT": 3015146, "Comune_cat": "C1AA", "Sez": " ", "Comune_amm": "F205", "Comune_descrizione": "MILANO", "Fascia": "D", "Zona_Descr": "BOVISA, BAUSAN, IMBONATI", "Zona": "D31", "LinkZona": "MI00004778", "Cod_tip_prev": 20, "Descr_tip_prev": "Abitazioni civili", "Stato_prev": "N", "Microzona": 0}, {"Area_territoriale": "NORD-OVEST", "Regione": "LOMBARDIA", "Prov": "MI", "Comune_ISTAT": 3015146, "Comune_cat": "C1AA", "Sez": " ", "Comune_amm": "F205", "Comune_descrizione": "MILANO", "Fascia": "D", "Zona_Descr": "BOVISASCA, AFFORI, P. ROSSI , COMASINA", "Zona": "D32", "LinkZona": "MI00004779", "Cod_tip_prev": 20, "Descr_tip_prev": "Abitazioni civili", "Stato_prev": "N", "Microzona": 0}, {"Area_territoriale": "NORD-OVEST", "Regione": "LOMBARDIA", "Prov": "MI", "Comune_ISTAT": 3015146, "Comune_cat": "C1AA", "Sez": " ", "Comune_amm": "F205", "Comune_descrizione": "MILANO", "Fascia": "D", "Zona_Descr": "NIGUARDA, BIGNAMI, PARCO NORD", "Zona": "D33", "LinkZona": "MI00004780", "Cod_tip_prev": 20, "Descr_tip_prev": "Abitazioni civili", "Stato_prev": "N", "Microzona": 0}, {"Area_territoriale": "NORD-OVEST", "Regione": "LOMBARDIA", "Prov": "MI", "Comune_ISTAT": 3015146, "Comune_cat": "C1AA", "Sez": " ", "Comune_amm": "F205", "Comune_descrizione": "MILANO", "Fascia": "D", "Zona_Descr": "SARCA, BICOCCA", "Zona": "D34", "LinkZona": "MI00004781", "Cod_tip_prev": 20, "Descr_tip_prev": "Abitazioni civili", "Stato_prev": "N", "Microzona": 0}, {"Area_territoriale": "NORD-OVEST", "Regione": "LOMBARDIA", "Prov": "MI", "Comune_ISTAT": 3015146, "Comune_cat": "C1AA", "Sez": " ", "Comune_amm": "F205", "Comune_descrizione": "MILANO", "Fascia": "D", "Zona_Descr": "MONZA, CRESCENZAGO, GORLA, QUARTIERE ADRIANO", "Zona": "D35", "LinkZona": "MI00004782", "Cod_tip_prev": 20, "Descr_tip_prev": "Abitazioni civili", "Stato_prev": "N", "Microzona": 0}, {"Area_territoriale": "NORD-OVEST", "Regione": "LOMBARDIA", "Prov": "MI", "Comune_ISTAT": 3015146, "Comune_cat": "C1AA", "Sez": " ", "Comune_amm": "F205", "Comune_descrizione": "MILANO", "Fascia": "D", "Zona_Descr": "MAGGIOLINA, PARCO TROTTER, LEONCAVALLO", "Zona": "D36", "LinkZona": "MI00004783", "Cod_tip_prev": 20, "Descr_tip_prev": "Abitazioni civili", "Stato_prev": "N", "Microzona": 0}, {"Area_territoriale": "NORD-OVEST", "Regione": "LOMBARDIA", "Prov": "MI", "Comune_ISTAT": 3015146, "Comune_cat": "C1AA", "Sez": " ", "Comune_amm": "F205", "Comune_descrizione": "MILANO", "Fascia": "D", "Zona_Descr": "FORLANINI, MECENATE, PONTE LAMBRO", "Zona": "D37", "LinkZona": "MI00011747", "Cod_tip_prev": 20, "Descr_tip_prev": "Abitazioni civili", "Stato_prev": "N", "Microzona": null}, {"Area_territoriale": "NORD-OVEST", "Regione": "LOMBARDIA", "Prov": "MI", "Comune_ISTAT": 3015146, "Comune_cat": "C1AA", "Sez": " ", "Comune_amm": "F205", "Comune_descrizione": "MILANO", "Fascia": "D", "Zona_Descr": "SANTA GIULIA, ROGOREDO", "Zona": "D38", "LinkZona": "MI00011748", "Cod_tip_prev": 20, "Descr_tip_prev": "Abitazioni civili", "Stato_prev": "N", "Microzona": null}, {"Area_territoriale": "NORD-OVEST", "Regione": "LOMBARDIA", "Prov": "MI", "Comune_ISTAT": 3015146, "Comune_cat": "C1AA", "Sez": " ", "Comune_amm": "F205", "Comune_descrizione": "MILANO", "Fascia": "D", "Zona_Descr": "CASCINA MERLATA, EXPO", "Zona": "D39", "LinkZona": "MI00011750", "Cod_tip_prev": 20, "Descr_tip_prev": "Abitazioni civili", "Stato_prev": "O", "Microzona": null}, {"Area_territoriale": "NORD-OVEST", "Regione": "LOMBARDIA", "Prov": "MI", "Comune_ISTAT": 3015146, "Comune_cat": "C1AA", "Sez": " ", "Comune_amm": "F205", "Comune_descrizione": "MILANO", "Fascia": "D", "Zona_Descr": "MUSOCCO, CERTOSA", "Zona": "D40", "LinkZona": "MI00011751", "Cod_tip_prev": 20, "Descr_tip_prev": "Abitazioni civili", "Stato_prev": "N", "Microzona": null}, {"Area_territoriale": "NORD-OVEST", "Regione": "LOMBARDIA", "Prov": "MI", "Comune_ISTAT": 3015146, "Comune_cat": "C1AA", "Sez": " ", "Comune_amm": "F205", "Comune_descrizione": "MILANO", "Fascia": "E", "Zona_Descr": "BAGGIO, Q. ROMANO, MUGGIANO", "Zona": "E5", "LinkZona": "MI00004784", "Cod_tip_prev": 20, "Descr_tip_prev": "Abitazioni civili", "Stato_prev": "N", "Microzona": 0}, {"Area_territoriale": "NORD-OVEST", "Regione": "LOMBARDIA", "Prov": "MI", "Comune_ISTAT": 3015146, "Comune_cat": "C1AA", "Sez": " ", "Comune_amm": "F205", "Comune_descrizione": "MILANO", "Fascia": "E", "Zona_Descr": "GALLARATESE, LAMPUGNANO, P. TRENNO, BONOLA", "Zona": "E6", "LinkZona": "MI00004785", "Cod_tip_prev": 20, "Descr_tip_prev": "Abitazioni civili", "Stato_prev": "N", "Microzona": 0}, {"Area_territoriale": "NORD-OVEST", "Regione": "LOMBARDIA", "Prov": "MI", "Comune_ISTAT": 3015146, "Comune_cat": "C1AA", "Sez": " ", "Comune_amm": "F205", "Comune_descrizione": "MILANO", "Fascia": "E", "Zona_Descr": "MISSAGLIA, GRATOSOGLIO", "Zona": "E7", "LinkZona": "MI00004786", "Cod_tip_prev": 20, "Descr_tip_prev": "Abitazioni civili", "Stato_prev": "N", "Microzona": 0}, {"Area_territoriale": "NORD-OVEST", "Regione": "LOMBARDIA", "Prov": "MI", "Comune_ISTAT": 3015146, "Comune_cat": "C1AA", "Sez": " ", "Comune_amm": "F205", "Comune_descrizione": "MILANO", "Fascia": "E", "Zona_Descr": "QUARTO OGGIARO, SACCO", "Zona": "E8", "LinkZona": "MI00004787", "Cod_tip_prev": 20, "Descr_tip_prev": "Abitazioni civili", "Stato_prev": "N", "Microzona": 0}, {"Area_territoriale": "NORD-OVEST", "Regione": "LOMBARDIA", "Prov": "MI", "Comune_ISTAT": 3015146, "Comune_cat": "C1AA", "Sez": " ", "Comune_amm": "F205", "Comune_descrizione": "MILANO", "Fascia": "R", "Zona_Descr": "RONCHETTO, CHIARAVALLE, RIPAMONTI", "Zona": "R2", "LinkZona": "MI00004391", "Cod_tip_prev": 0, "Descr_tip_prev": "Non presente", "Stato_prev": " ", "Microzona": 0}]